{
	"class" : {
		"announcer" : "SvenVanCaekenberghe 12/8/2014 22:58" },
	"instance" : {
		"announcer" : "SvenVanCaekenberghe 12/8/2014 22:59",
		"buildInspectorView" : "SvenVanCaekenberghe 1/16/2015 16:48",
		"chartViewWith:" : "SvenVanCaekenberghe 1/18/2015 16:58",
		"data" : "SvenVanCaekenberghe 12/8/2014 22:06",
		"data:" : "SvenVanCaekenberghe 12/8/2014 22:07",
		"dataSet" : "SvenVanCaekenberghe 1/16/2015 16:51",
		"elementFrom:at:" : "SvenVanCaekenberghe 1/8/2015 12:39",
		"emit" : "SvenVanCaekenberghe 12/8/2014 22:59",
		"gtInspectorView2In:" : "SvenVanCaekenberghe 1/17/2015 00:02",
		"gtInspectorViewIn:" : "SvenVanCaekenberghe 1/17/2015 00:02",
		"highlight:" : "SvenVanCaekenberghe 1/8/2015 10:39",
		"withLegend:" : "SvenVanCaekenberghe 1/8/2015 10:29" } }
